metaflow_extensions/resource_tracker/plugins/mfextinit_resource_tracker.py
metaflow_extensions/resource_tracker/plugins/cards/tracked_resources/__init__.py
metaflow_extensions/resource_tracker/plugins/cards/tracked_resources/card_decorator.py
metaflow_extensions/resource_tracker/plugins/cards/tracked_resources/resource_tracker/__init__.py
metaflow_extensions/resource_tracker/plugins/cards/tracked_resources/resource_tracker/_version.py
metaflow_extensions/resource_tracker/plugins/cards/tracked_resources/resource_tracker/cloud_info.py
metaflow_extensions/resource_tracker/plugins/cards/tracked_resources/resource_tracker/column_maps.py
metaflow_extensions/resource_tracker/plugins/cards/tracked_resources/resource_tracker/dummy_workloads.py
metaflow_extensions/resource_tracker/plugins/cards/tracked_resources/resource_tracker/helpers.py
metaflow_extensions/resource_tracker/plugins/cards/tracked_resources/resource_tracker/keeper.py
metaflow_extensions/resource_tracker/plugins/cards/tracked_resources/resource_tracker/nvidia.py
metaflow_extensions/resource_tracker/plugins/cards/tracked_resources/resource_tracker/report.py
metaflow_extensions/resource_tracker/plugins/cards/tracked_resources/resource_tracker/server_info.py
metaflow_extensions/resource_tracker/plugins/cards/tracked_resources/resource_tracker/tiny_bars.py
metaflow_extensions/resource_tracker/plugins/cards/tracked_resources/resource_tracker/tiny_data_frame.py
metaflow_extensions/resource_tracker/plugins/cards/tracked_resources/resource_tracker/tracker.py
metaflow_extensions/resource_tracker/plugins/cards/tracked_resources/resource_tracker/tracker_procfs.py
metaflow_extensions/resource_tracker/plugins/cards/tracked_resources/resource_tracker/tracker_psutil.py
metaflow_extensions/resource_tracker/plugins/cards/tracked_resources/resource_tracker/report_template/custom.css
metaflow_extensions/resource_tracker/plugins/cards/tracked_resources/resource_tracker/report_template/helpers.js
resource_tracker-0.4.2.dist-info/METADATA
resource_tracker-0.4.2.dist-info/WHEEL
resource_tracker-0.4.2.dist-info/top_level.txt
resource_tracker-0.4.2.dist-info/RECORD
