Metadata-Version: 2.4
Name: resource-tracker
Version: 0.4.2
Summary: Lightweight Python package for monitoring process and system resource usage with optional Metaflow integration for cloud cost optimization.
Author-email: Gergely Daroczi <daroczig@sparecores.com>
License-Expression: MPL-2.0
Project-URL: repository, https://github.com/SpareCores/resource-tracker
Project-URL: issues, https://github.com/SpareCores/resource-tracker/issues
Project-URL: documentation, https://sparecores.github.io/resource-tracker/
Project-URL: changelog, https://github.com/SpareCores/resource-tracker/blob/main/CHANGELOG.md
Keywords: resource-monitor,metaflow
Classifier: Programming Language :: Python :: 3
Classifier: Operating System :: POSIX :: Linux
Classifier: Operating System :: MacOS
Classifier: Operating System :: Microsoft :: Windows
Provides-Extra: dev
Requires-Dist: pytest; extra == "dev"
Requires-Dist: metaflow; extra == "dev"
Requires-Dist: psutil; extra == "dev"
Provides-Extra: metaflow
Requires-Dist: metaflow; extra == "metaflow"
Provides-Extra: psutil
Requires-Dist: psutil; extra == "psutil"
Provides-Extra: mkdocs
Requires-Dist: markdown; extra == "mkdocs"
Requires-Dist: mkdocs; extra == "mkdocs"
Requires-Dist: mkdocs-material[imaging]; extra == "mkdocs"
Requires-Dist: mkdocs-material-extensions; extra == "mkdocs"
Requires-Dist: mkdocs-autorefs; extra == "mkdocs"
Requires-Dist: mkdocs-gen-files; extra == "mkdocs"
Requires-Dist: mkdocs-literate-nav; extra == "mkdocs"
Requires-Dist: mkdocs-section-index; extra == "mkdocs"
Requires-Dist: mkdocstrings[python]>=0.18; extra == "mkdocs"
Requires-Dist: mkdocs-api-autonav; extra == "mkdocs"
